edgar/__init__.py
edgar/company.py
edgar/document.py
edgar/edgar.py
edgar/txtml.py
edgar/utils.py
edgar/xbrl.py
edgar-5.6.2.dist-info/LICENSE
edgar-5.6.2.dist-info/METADATA
edgar-5.6.2.dist-info/WHEEL
edgar-5.6.2.dist-info/top_level.txt
edgar-5.6.2.dist-info/RECORD
