Metadata-Version: 2.1
Name: edgar
Version: 5.6.2
Summary: Scrape data from SEC's EDGAR
Home-page: https://github.com/joeyism/py-edgar
Download-URL: https://github.com/joeyism/py-edgar/archive/5.6.2.tar.gz
Author: Joey Sham
Author-email: sham.joey@gmail.com
Keywords: edgar,sec
License-File: LICENSE
Requires-Dist: requests
Requires-Dist: lxml
Requires-Dist: tqdm
Requires-Dist: rapidfuzz
